cost_of_code/__init__.py
cost_of_code/code_tokenizer.py
cost_of_code/cost_estimator.py
cost_of_code/git_handler.py
cost_of_code/main.py
cost_of_code/test_code_tokenizer.py
cost_of_code-0.1.4.dist-info/LICENSE
cost_of_code-0.1.4.dist-info/METADATA
cost_of_code-0.1.4.dist-info/WHEEL
cost_of_code-0.1.4.dist-info/entry_points.txt
cost_of_code-0.1.4.dist-info/top_level.txt
cost_of_code-0.1.4.dist-info/RECORD
