Metadata-Version: 2.1
Name: cost-of-code
Version: 0.1.4
Summary: How much would it have cost if GPT-4 had written your code?
Home-page: https://github.com/Ghost---Shadow/cost-of-code
Author: Souradeep Nanda
Classifier: Development Status :: 3 - Alpha
Classifier: Intended Audience :: Developers
Classifier: Topic :: Software Development :: Build Tools
Classifier: License :: OSI Approved :: MIT License
Classifier: Programming Language :: Python :: 3
Classifier: Programming Language :: Python :: 3.6
Classifier: Programming Language :: Python :: 3.7
Classifier: Programming Language :: Python :: 3.8
Classifier: Programming Language :: Python :: 3.9
Requires-Python: >=3.6
License-File: LICENSE
Requires-Dist: GitPython
Requires-Dist: tiktoken
Requires-Dist: pathspec
Requires-Dist: tqdm
